janus_remote/__init__.py
janus_remote/approval_hook.py
janus_remote/cli.py
janus_remote/pty_capture.py
janus_remote-0.9.12.dist-info/licenses/LICENSE
janus_remote-0.9.12.dist-info/METADATA
janus_remote-0.9.12.dist-info/WHEEL
janus_remote-0.9.12.dist-info/entry_points.txt
janus_remote-0.9.12.dist-info/top_level.txt
janus_remote-0.9.12.dist-info/RECORD
