Metadata-Version: 2.4
Name: janus-remote
Version: 0.9.12
Summary: Voice-to-text paste and approval bridge for Claude CLI on remote SSH sessions
Author: He Who Seeks
License-Expression: MIT
Project-URL: Homepage, https://github.com/anthropics/janus
Project-URL: Repository, https://github.com/anthropics/janus
Keywords: claude,voice,ssh,remote,paste,janus
Classifier: Development Status :: 4 - Beta
Classifier: Environment :: Console
Classifier: Intended Audience :: Developers
Classifier: Operating System :: POSIX :: Linux
Classifier: Operating System :: MacOS
Classifier: Programming Language :: Python :: 3
Classifier: Programming Language :: Python :: 3.8
Classifier: Programming Language :: Python :: 3.9
Classifier: Programming Language :: Python :: 3.10
Classifier: Programming Language :: Python :: 3.11
Classifier: Programming Language :: Python :: 3.12
Classifier: Topic :: Software Development :: Libraries :: Python Modules
Requires-Python: >=3.8
License-File: LICENSE
Requires-Dist: websocket-client>=1.0.0
Dynamic: license-file
